{"dependencies":[{"name":"./take","loc":{"line":5,"column":22}}],"generated":{"js":"'use strict';\n\nObject.defineProperty(exports, \"__esModule\", {\n  value: true\n});\n\nvar _take = require('./take');\n\nObject.defineProperty(exports, 'default', {\n  enumerable: true,\n  get: function () {\n    return _interopRequireDefault(_take).default;\n  }\n});\n\nfunction _interopRequireDefault(obj) { return obj && obj.__esModule ? obj : { default: obj }; }","map":{"mappings":[{"name":"default","generated":{"line":12,"column":41},"source":"node_modules/underscore-es/head.js","original":{"line":5,"column":8}}],"sources":{"node_modules/underscore-es/head.js":"// `_head` : a collection's function\n// ----------------------------------\n\n// The cornerstone, a `head` implementation, aka `take`.\nexport {default} from './take';"},"lineCount":null}},"hash":"e19ea4f429050a1e38daeeb962a37bdc","cacheData":{"env":{}}}